MANIFEST.in
setup.py
oncondition/__init__.py
oncondition/admin.py
oncondition/apps.py
oncondition/events.py
oncondition/models.py
oncondition/signals.py
oncondition/tasks.py
oncondition/util.py
oncondition.egg-info/PKG-INFO
oncondition.egg-info/SOURCES.txt
oncondition.egg-info/dependency_links.txt
oncondition.egg-info/requires.txt
oncondition.egg-info/top_level.txt
test/test_events.py