Metadata-Version: 1.0
Name: oncondition
Version: 0.7
Summary: Event classes that fire actions on conditions. Supports Django.
Home-page: http://github.com/futurice/oncondition
Author: Jussi Vaihia
Author-email: jussi.vaihia@futurice.com
License: BSD
Keywords: django event condition transparency
Platform: UNKNOWN
